mjkit/__init__.py
mjkit/cache/__init__.py
mjkit/cache/midnight_time_cache.py
mjkit/cache/time_cache.py
mjkit/errors/__init__.py
mjkit/errors/error.py
mjkit/huggingface/__init__.py
mjkit/huggingface/create_readme.py
mjkit/init_generator/__init__.py
mjkit/init_generator/base/__init__.py
mjkit/init_generator/base/base_init_generator.py
mjkit/init_generator/init_generator.py
mjkit/init_generator/interfaces/__init__.py
mjkit/init_generator/interfaces/abstract_init_generator.py
mjkit/mixin/__init__.py
mjkit/mixin/attribute_printer_mixin.py
mjkit/mixin/dataclass_pretty_str_mixin.py
mjkit/mixin/date_validator_mixin.py
mjkit/mixin/kwargs_validation_mixin.py
mjkit/mixin/logging_mixin.py
mjkit/mixin/prevent_override_mixin.py
mjkit/support/__init__.py
mjkit/support/get_exp_save_path.py
mjkit/utiles/__init__.py
mjkit/utiles/camel_to_snake.py
mjkit/utiles/delete_file.py
mjkit/utiles/extract_delimited_blocks.py
mjkit/utiles/financial_dates.py
mjkit/utiles/format_elapsed_time.py
mjkit/utiles/get_folder_path.py
mjkit/utiles/get_holiday_calendar.py
mjkit/utiles/get_logger.py
mjkit/utiles/get_search_space_len.py
mjkit/utiles/pickle_utiles.py
mjkit/utiles/save_text_to_file.py
mjkit/utiles/suppress_stdout.py
mjkit/utiles/timeit.py
mjkit/utiles/validate_date_format.py
mjkit/utiles/validate_yyyymm_format.py
mjkit-0.0.21.dist-info/LICENSE
mjkit-0.0.21.dist-info/METADATA
mjkit-0.0.21.dist-info/WHEEL
mjkit-0.0.21.dist-info/RECORD
