Metadata-Version: 2.3
Name: mjkit
Version: 0.0.21
Summary: 
License: SEE LICENSE FILE
Author: devmjun
Author-email: dev.mjun@gmail.com
Requires-Python: >=3.10, <4
Classifier: Programming Language :: Python :: 3.10
Classifier: Programming Language :: Python :: 3.11
Classifier: Programming Language :: Python :: 3.12
Classifier: Programming Language :: Python :: 3.13
Classifier: Programming Language :: Python :: 3 :: Only
Requires-Dist: holidays (>=0.7.0,<1.0.0)
Project-URL: Homepage, https://github.com/devmjun/mjkit
Project-URL: Repository, https://github.com/devmjun/mjkit
